Metadata-Version: 1.1
Name: choraoipsum
Version: 0.0.1
Summary: Um gerador verbatim com um jeito sk8 de ser
Home-page: https://github.com/igr-santos/choraoipsum
Author: Charlie Brown
Author-email: choraoipsum@googlegroups.com
License: MIT
Keywords: sample setuptools development
Platform: UNKNOWN
Classifier: Development Status :: 3 - Alpha
Classifier: Intended Audience :: Developers
Classifier: Topic :: Software Development :: Build Tools
Classifier: License :: OSI Approved :: MIT License
Classifier: Programming Language :: Python :: 2
Classifier: Programming Language :: Python :: 2.6
Classifier: Programming Language :: Python :: 2.7
Classifier: Programming Language :: Python :: 3
Classifier: Programming Language :: Python :: 3.3
Classifier: Programming Language :: Python :: 3.4
Classifier: Programming Language :: Python :: 3.5
